pykuda/__init__.py
pykuda/constants.py
pykuda/pykuda.py
pykuda/service_type_utils.py
pykuda/utils.py
pykuda/classes/py_kuda_response.py
pykuda/classes/service_type.py
pykuda-1.0.6.dist-info/LICENCE
pykuda-1.0.6.dist-info/METADATA
pykuda-1.0.6.dist-info/WHEEL
pykuda-1.0.6.dist-info/top_level.txt
pykuda-1.0.6.dist-info/RECORD
