Metadata-Version: 2.1
Name: pykuda
Version: 1.0.6
Summary: A python package that simplifies using the Kuda Bank Api
Author-email: TemiTope Kayode <cwt@temilimited.com>
Project-URL: Homepage, https://github.com/sir-temi/pykuda
Project-URL: Bug Tracker, https://github.com/sir-temi/pykuda/issues
Keywords: kuda bank,pykuda,Open API
Classifier: Programming Language :: Python :: 3
Classifier: License :: OSI Approved :: MIT License
Classifier: Operating System :: OS Independent
Requires-Python: >=3.10
License-File: LICENCE
Requires-Dist: requests
Requires-Dist: python-decouple
